MANIFEST.in
README.md
setup.py
django_pico.egg-info/PKG-INFO
django_pico.egg-info/SOURCES.txt
django_pico.egg-info/dependency_links.txt
django_pico.egg-info/requires.txt
django_pico.egg-info/top_level.txt
djpico/__init__.py
djpico/urls.py
djpico/views.py