Metadata-Version: 1.1
Name: django-pico
Version: 0.0.1
Summary: A Django wrapper for the Pico web app framework
Home-page: http://github.com/fergalwalsh/django-pico
Author: Fergal Walsh
Author-email: fergalwalsh@gmail.com
License: BSD License
Download-URL: https://github.com/fergalwalsh/django-pico/tarball/0.0.1
Platform: UNKNOWN
Classifier: Environment :: Web Environment
Classifier: Framework :: Django
Classifier: Intended Audience :: Developers
Classifier: License :: OSI Approved :: BSD License
Classifier: Operating System :: OS Independent
Classifier: Programming Language :: Python
Classifier: Programming Language :: Python :: 2
Classifier: Programming Language :: Python :: 2.7
Classifier: Topic :: Internet :: WWW/HTTP
Classifier: Topic :: Internet :: WWW/HTTP :: Dynamic Content
